apicrafter/__init__.py
apicrafter/auth.py
apicrafter/auth_manager.py
apicrafter/body.py
apicrafter/cli.py
apicrafter/field_prompter.py
apicrafter/http_client.py
apicrafter/interactive.py
apicrafter/renderer.py
apicrafter/schema_loader.py
apicrafter/storage.py
apicrafter/validator.py
apicrafter/tests/__init__.py
apicrafter/tests/test_http_client.py
apicrafter/tests/test_storage.py
apicrafter_cli-0.1.7.dist-info/licenses/LICENSE
apicrafter_cli-0.1.7.dist-info/METADATA
apicrafter_cli-0.1.7.dist-info/WHEEL
apicrafter_cli-0.1.7.dist-info/entry_points.txt
apicrafter_cli-0.1.7.dist-info/top_level.txt
apicrafter_cli-0.1.7.dist-info/RECORD
