Metadata-Version: 2.4
Name: apicrafter-cli
Version: 0.1.7
Summary: A terminal-first, interactive API client that brings Postman-like features into the CLI
Author-email: Yash Singh <yashs3326@gmail.com>
Maintainer-email: Yash Singh <yashs3326@gmail.com>
License-Expression: MIT
Project-URL: Homepage, https://github.com/yash-vrdhan/apicrafter
Project-URL: Repository, https://github.com/yash-vrdhan/apicrafter
Project-URL: Documentation, https://github.com/yash-vrdhan/apicrafter#readme
Project-URL: Bug Tracker, https://github.com/yash-vrdhan/apicrafter/issues
Keywords: api,http,client,cli,postman,rest
Classifier: Development Status :: 4 - Beta
Classifier: Intended Audience :: Developers
Classifier: Programming Language :: Python :: 3
Classifier: Programming Language :: Python :: 3.9
Classifier: Programming Language :: Python :: 3.10
Classifier: Programming Language :: Python :: 3.11
Classifier: Programming Language :: Python :: 3.12
Classifier: Topic :: Software Development :: Testing
Classifier: Topic :: Internet :: WWW/HTTP
Classifier: Topic :: Internet :: WWW/HTTP :: HTTP Servers
Classifier: Topic :: Software Development :: Libraries :: Python Modules
Classifier: Topic :: System :: Networking
Classifier: Environment :: Console
Classifier: Operating System :: OS Independent
Requires-Python: >=3.9
License-File: LICENSE
Requires-Dist: typer>=0.9.0
Requires-Dist: httpx>=0.24.0
Requires-Dist: rich>=13.0.0
Requires-Dist: questionary>=2.0.0
Requires-Dist: pydantic>=2.0.0
Requires-Dist: pyyaml>=6.0.0
Requires-Dist: click>=8.0.0
Provides-Extra: dev
Requires-Dist: pytest>=7.0.0; extra == "dev"
Requires-Dist: pytest-cov>=4.0.0; extra == "dev"
Requires-Dist: black>=23.0.0; extra == "dev"
Requires-Dist: isort>=5.12.0; extra == "dev"
Requires-Dist: mypy>=1.0.0; extra == "dev"
Requires-Dist: pre-commit>=3.0.0; extra == "dev"
Dynamic: license-file
